datum/__init__.py
datum/apps.py
datum/models.py
datum/version.py
datum/management/__init__.py
datum/management/commands/__init__.py
datum/management/commands/clear_expired_datums.py
datum/migrations/0001_initial.py
datum/migrations/__init__.py
datum/tests/__init__.py
datum/tests/management_command_tests.py
datum/tests/model_tests.py
django_datum-0.1.1.dist-info/DESCRIPTION.rst
django_datum-0.1.1.dist-info/METADATA
django_datum-0.1.1.dist-info/metadata.json
django_datum-0.1.1.dist-info/RECORD
django_datum-0.1.1.dist-info/top_level.txt
django_datum-0.1.1.dist-info/WHEEL
