Metadata-Version: 2.0
Name: django-datum
Version: 0.1.1
Summary: UNKNOWN
Home-page: https://github.com/ambitioninc/django-datum
Author: Josh Marlow
Author-email: opensource@ambition.com
License: MIT
Platform: UNKNOWN
Classifier: Programming Language :: Python
Classifier: Programming Language :: Python :: 2.7
Classifier: Programming Language :: Python :: 3.4
Classifier: Intended Audience :: Developers
Classifier: License :: OSI Approved :: MIT License
Classifier: Operating System :: OS Independent
Classifier: Framework :: Django
Requires-Dist: Django (>=1.7)
Requires-Dist: jsonfield
